cfsem-3.1.0.dist-info/METADATA
cfsem-3.1.0.dist-info/WHEEL
cfsem-3.1.0.dist-info/licenses/LICENSE
cfsem.libs/libgcc_s-262c4f60.so.1
cfsem/__init__.py
cfsem/bindings.py
cfsem/cfsem.cpython-311-arm-linux-musleabihf.so
cfsem/py.typed
cfsem/solenoid_stress/__init__.py
cfsem/solenoid_stress/solenoid_1d.py
cfsem/solenoid_stress/solenoid_handcalc.py
cfsem/solenoid_stress/thick_wall_cylinder_handcalc.py
cfsem/types.py
cfsem-3.1.0.dist-info/RECORD
