Metadata-Version: 2.4
Name: cfsem
Version: 3.1.0
Classifier: Programming Language :: Rust
Classifier: Programming Language :: Python :: Implementation :: CPython
Classifier: Programming Language :: Python :: Implementation :: PyPy
Requires-Dist: numpy>=2
Requires-Dist: interpn[pydantic]>=0.8.2,<0.9
Requires-Dist: findiff>=0.12.1
Requires-Dist: pydantic>=2
Requires-Dist: pydantic-numpy>=6
License-File: LICENSE
Summary: Quasi-steady electromagnetics including filamentized approximations, Biot-Savart, and Grad-Shafranov.
Home-Page: https://github.com/cfs-energy/cfsem-py
Author-email: Commonwealth Fusion Systems <jlogan@cfs.energy>
License-Expression: MIT
Requires-Python: >=3.10, <3.14
